Metadata-Version: 2.1
Name: annotate-lineinfo
Version: 0.1
Summary: Annotate IDA with source and line number information from a PDB
Home-page: https://github.com/clarkb7/annotate_lineinfo
Author: Branden Clark
Author-email: clark@rpis.ec
License: MIT
Keywords: IDA IDAPython PDB
Platform: UNKNOWN
Classifier: Development Status :: 3 - Alpha
Classifier: Intended Audience :: Developers
Classifier: License :: OSI Approved :: MIT License
Classifier: Natural Language :: English
Classifier: Operating System :: Microsoft :: Windows
Classifier: Programming Language :: Python
Classifier: Topic :: Security
Classifier: Topic :: Software Development :: Disassemblers
